stochtree_cpp.cpython-39-x86_64-linux-gnu.so
stochtree/__init__.py
stochtree/bart.py
stochtree/bcf.py
stochtree/calibration.py
stochtree/config.py
stochtree/data.py
stochtree/forest.py
stochtree/kernel.py
stochtree/preprocessing.py
stochtree/random_effects.py
stochtree/sampler.py
stochtree/serialization.py
stochtree/utils.py
stochtree.libs/libgomp-a34b3233.so.1.0.0
stochtree-0.2.1.dist-info/METADATA
stochtree-0.2.1.dist-info/WHEEL
stochtree-0.2.1.dist-info/top_level.txt
stochtree-0.2.1.dist-info/RECORD
stochtree-0.2.1.dist-info/licenses/CPP_DEPS_LICENSE.md
stochtree-0.2.1.dist-info/licenses/LICENSE.md
