Metadata-Version: 2.1
Name: stochtree
Version: 0.2.1
Summary: Stochastic Tree Ensembles for Machine Learning and Causal Inference
Author-email: Drew Herren <drewherrenopensource@gmail.com>
License: MIT
Project-URL: Homepage, https://stochtree.ai/
Project-URL: Documentation, https://stochtree.ai/python_docs/index.html
Project-URL: Repository, https://github.com/StochasticTree/stochtree
Project-URL: Issues, https://github.com/StochasticTree/stochtree/issues
Classifier: Development Status :: 4 - Beta
Classifier: Intended Audience :: Science/Research
Classifier: License :: OSI Approved :: MIT License
Classifier: Operating System :: MacOS
Classifier: Operating System :: Microsoft :: Windows
Classifier: Operating System :: POSIX :: Linux
Classifier: Programming Language :: Python :: 3.8
Classifier: Programming Language :: Python :: 3.9
Classifier: Programming Language :: Python :: 3.10
Classifier: Programming Language :: Python :: 3.11
Classifier: Programming Language :: Python :: 3.12
Classifier: Programming Language :: Python :: 3.13
Classifier: Topic :: Scientific/Engineering :: Artificial Intelligence
Requires-Python: >=3.8.0
License-File: LICENSE.md
License-File: CPP_DEPS_LICENSE.md
Provides-Extra: test
Requires-Dist: pytest>=6.0; extra == "test"
